auto_face_recognition/__init__.py
auto_face_recognition/features/__init__.py
auto_face_recognition/features/face_recognition/dataset_create.py
auto_face_recognition/features/face_recognition/predict.py
auto_face_recognition/features/face_recognition/train.py
auto_face_recognition-0.0.3.dist-info/License.txt
auto_face_recognition-0.0.3.dist-info/METADATA
auto_face_recognition-0.0.3.dist-info/WHEEL
auto_face_recognition-0.0.3.dist-info/top_level.txt
auto_face_recognition-0.0.3.dist-info/RECORD
