Metadata-Version: 2.1
Name: auto-face-recognition
Version: 0.0.3
Summary: auto_face_recognition is Tensorflow based python library for fast face recognition
Home-page: https://github.com/Dipeshpal/auto_face_recognition
Author: Dipesh
Author-email: dipeshpal17@gmail.com
License: UNKNOWN
Platform: UNKNOWN
Classifier: Programming Language :: Python :: 3
Classifier: License :: OSI Approved :: MIT License
Classifier: Operating System :: OS Independent
Requires-Python: >=3.6
Requires-Dist: numpy (==1.18.5)
Requires-Dist: opencv-contrib-python
Requires-Dist: tensorflow
Requires-Dist: matplotlib
